<?xml version="1.0" encoding="ISO-8859-1"?>
<explain>
  <serverInfo protocol="Z39.50">
    <host>z3950.dbf.ddb.de</host>
    <port>210</port>
    <database>iltis</database>
    <authentication>
        <user>???</user>
        <password>???</password>
    </authentication>
    <encoding>marc-8</encoding>
  </serverInfo>
    <databaseInfo>
      <title primary="true" lang="en">Die Deutsche Bibliothek</title>
      <author>Die Deutsche Bibliothek</author>
   </databaseInfo>
   <metaInfo>
     <dateModified>2005-03-02T00:46:42ZCET</dateModified>
   </metaInfo>
    <indexInfo>
      <index search="true">
        <title primary="true" lang="en">Personal name</title>
        <map primary="true">
          <attr type="1" set="bib-1">1</attr>
        </map>
      </index>
      <index search="true">
        <title primary="true" lang="en">Corporate name</title>
        <map primary="true">
          <attr type="1" set="bib-1">2</attr>
        </map>
      </index>
      <index search="true">
        <title primary="true" lang="en">Title</title>
        <map primary="true">
          <attr type="1" set="bib-1">4</attr>
        </map>
      </index>
      <index search="true">
        <title primary="true" lang="en">Title uniform</title>
        <map primary="true">
          <attr type="1" set="bib-1">6</attr>
        </map>
      </index>
      <index search="true">
        <title primary="true" lang="en">ISBN</title>
        <map primary="true">
          <attr type="1" set="bib-1">7</attr>
        </map>
      </index>
      <index search="true">
        <title primary="true" lang="en">ISSN</title>
        <map primary="true">
          <attr type="1" set="bib-1">8</attr>
        </map>
      </index>
      <index search="true">
        <title primary="true" lang="en">Local number</title>
        <map primary="true">
          <attr type="1" set="bib-1">12</attr>
        </map>
      </index>
      <index search="true">
        <title primary="true" lang="en">Dewey classificat</title>
        <map primary="true">
          <attr type="1" set="bib-1">13</attr>
        </map>
      </index>
      <index search="true">
        <title primary="true" lang="en">Local classification</title>
        <map primary="true">
          <attr type="1" set="bib-1">20</attr>
        </map>
      </index>
      <index search="true">
        <title primary="true" lang="en">Subject heading</title>
        <map primary="true">
          <attr type="1" set="bib-1">21</attr>
        </map>
      </index>
      <index search="true">
        <title primary="true" lang="en">Subject rswk</title>
        <map primary="true">
          <attr type="1" set="bib-1">46</attr>
        </map>
      </index>
      <index search="true">
        <title primary="true" lang="en">No. nat'l biblio.</title>
        <map primary="true">
          <attr type="1" set="bib-1">48</attr>
        </map>
      </index>
      <index search="true">
        <title primary="true" lang="en">Number db</title>
        <map primary="true">
          <attr type="1" set="bib-1">52</attr>
        </map>
      </index>
      <index search="true">
        <title primary="true" lang="en">Number local call</title>
        <map primary="true">
          <attr type="1" set="bib-1">53</attr>
        </map>
      </index>
      <index search="true">
        <title primary="true" lang="en">Code--language</title>
        <map primary="true">
          <attr type="1" set="bib-1">54</attr>
        </map>
      </index>
      <index search="true">
        <title primary="true" lang="en">Code--geographic area</title>
        <map primary="true">
          <attr type="1" set="bib-1">55</attr>
        </map>
      </index>
      <index search="true">
        <title primary="true" lang="en">Author-name personal</title>
        <map primary="true">
          <attr type="1" set="bib-1">1004</attr>
        </map>
      </index>
      <index search="true">
        <title primary="true" lang="en">Author-name corporate</title>
        <map primary="true">
          <attr type="1" set="bib-1">1005</attr>
        </map>
      </index>
      <index search="true">
        <title primary="true" lang="en">Identifier--standard</title>
        <map primary="true">
          <attr type="1" set="bib-1">1007</attr>
        </map>
      </index>
      <index search="true">
        <title primary="true" lang="en">Subject name -- personal</title>
        <map primary="true">
          <attr type="1" set="bib-1">1009</attr>
        </map>
      </index>
      <index search="true">
        <title primary="true" lang="en">Date/time last modified</title>
        <map primary="true">
          <attr type="1" set="bib-1">1012</attr>
        </map>
      </index>
      <index search="true">
        <title primary="true" lang="en">Publisher</title>
        <map primary="true">
          <attr type="1" set="bib-1">1018</attr>
        </map>
      </index>
    </indexInfo>
   <recordInfo>
     <recordSyntax name="SUTRS">
       <elementSet name="F"></elementSet>
     </recordSyntax>
   </recordInfo>
</explain>
